edit4config/__init__.py
edit4config/edit4config.py
edit4config-2025.9.14.dist-info/licenses/LICENSE
edit4config-2025.9.14.dist-info/METADATA
edit4config-2025.9.14.dist-info/WHEEL
edit4config-2025.9.14.dist-info/top_level.txt
edit4config-2025.9.14.dist-info/RECORD
