Metadata-Version: 2.4
Name: edit4config
Version: 2025.9.14
Summary: Nokia SROS, Cisco IOS style (parent/child with space indent) config edit (add/delete/replace) with regex
Author: Umur Arslan
License: MIT License
Project-URL: Homepage, https://github.com/umurarslan/edit4config
Classifier: Programming Language :: Python :: 3
Classifier: License :: OSI Approved :: MIT License
Classifier: Operating System :: OS Independent
Requires-Python: >=3.9
License-File: LICENSE
Dynamic: license-file
